lynx/__init__.py
lynx/kite.py
lynx/kite.py-bak
lynx/operations.py
lynxkite_client-5.4.1.dist-info/METADATA
lynxkite_client-5.4.1.dist-info/WHEEL
lynxkite_client-5.4.1.dist-info/RECORD
